LICENSE.md
MANIFEST.in
README.md
setup.cfg
setup.py
jupyter_kernel_gateway_quarc_custom_fix.egg-info/PKG-INFO
jupyter_kernel_gateway_quarc_custom_fix.egg-info/SOURCES.txt
jupyter_kernel_gateway_quarc_custom_fix.egg-info/dependency_links.txt
jupyter_kernel_gateway_quarc_custom_fix.egg-info/requires.txt
jupyter_kernel_gateway_quarc_custom_fix.egg-info/top_level.txt
kernel_gateway_quarc_custom_fix/__init__.py
kernel_gateway_quarc_custom_fix/__main__.py
kernel_gateway_quarc_custom_fix/_version.py
kernel_gateway_quarc_custom_fix/gatewayapp.py
kernel_gateway_quarc_custom_fix/mixins.py
kernel_gateway_quarc_custom_fix/base/__init__.py
kernel_gateway_quarc_custom_fix/base/handlers.py
kernel_gateway_quarc_custom_fix/jupyter_websocket/__init__.py
kernel_gateway_quarc_custom_fix/jupyter_websocket/handlers.py
kernel_gateway_quarc_custom_fix/notebook_http/__init__.py
kernel_gateway_quarc_custom_fix/notebook_http/errors.py
kernel_gateway_quarc_custom_fix/notebook_http/handlers.py
kernel_gateway_quarc_custom_fix/notebook_http/request_utils.py
kernel_gateway_quarc_custom_fix/notebook_http/cell/__init__.py
kernel_gateway_quarc_custom_fix/notebook_http/cell/parser.py
kernel_gateway_quarc_custom_fix/notebook_http/swagger/__init__.py
kernel_gateway_quarc_custom_fix/notebook_http/swagger/builders.py
kernel_gateway_quarc_custom_fix/notebook_http/swagger/handlers.py
kernel_gateway_quarc_custom_fix/notebook_http/swagger/parser.py
kernel_gateway_quarc_custom_fix/services/__init__.py
kernel_gateway_quarc_custom_fix/services/kernels/__init__.py
kernel_gateway_quarc_custom_fix/services/kernels/handlers.py
kernel_gateway_quarc_custom_fix/services/kernels/manager.py
kernel_gateway_quarc_custom_fix/services/kernels/pool.py
kernel_gateway_quarc_custom_fix/services/kernelspecs/__init__.py
kernel_gateway_quarc_custom_fix/services/kernelspecs/handlers.py
kernel_gateway_quarc_custom_fix/services/sessions/__init__.py
kernel_gateway_quarc_custom_fix/services/sessions/handlers.py
kernel_gateway_quarc_custom_fix/services/sessions/sessionmanager.py